BOOME/BOOME_algorithm.py
BOOME/__init__.py
BOOME-0.0.2.dist-info/LICENSE.txt
BOOME-0.0.2.dist-info/METADATA
BOOME-0.0.2.dist-info/WHEEL
BOOME-0.0.2.dist-info/top_level.txt
BOOME-0.0.2.dist-info/RECORD
