Metadata-Version: 2.1
Name: BOOME
Version: 0.0.2
Summary: This package aims to employ the boosting algorithm to do variable selection and estimation for measurement error in binary responses and high-dimensional covariates.
Author: Qin-Ying Ou Yang and Li-Pang Chen
Author-email: 109354014@nccu.edu.tw, lchen723@nccu.edu.tw
License: UNKNOWN
Platform: UNKNOWN
Classifier: Programming Language :: Python :: 3
Classifier: License :: OSI Approved :: MIT License
Classifier: Operating System :: OS Independent
Requires-Python: >=3.6
License-File: LICENSE.txt
